pypmi/__init__.py
pypmi/_info.py
pypmi/_version.py
pypmi/bids.py
pypmi/cluster.py
pypmi/fetchers.py
pypmi/info.py
pypmi/loaders.py
pypmi/utils.py
pypmi/data/genetics.json
pypmi/data/heuristic.py
pypmi/data/sessions.txt
pypmi/data/studydata.json
pypmi/tests/__init__.py
pypmi/tests/conftest.py
pypmi/tests/test_fetchers.py
pypmi/tests/test_loaders.py
pypmi/tests/test_utils.py
pypmi-0.3.dist-info/LICENSE
pypmi-0.3.dist-info/METADATA
pypmi-0.3.dist-info/WHEEL
pypmi-0.3.dist-info/top_level.txt
pypmi-0.3.dist-info/RECORD
