Metadata-Version: 2.1
Name: pypmi
Version: 0.3
Summary: pypmi is a Python toolbox for working with data from the Parkinson's Progression Markers Initiative (PPMI)
Home-page: http://github.com/rmarkello/pypmi
Author: pypmi developers
Author-email: rossmarkello@gmail.com
Maintainer: Ross Markello
Maintainer-email: rossmarkello@gmail.com
License: BSD-3
Download-URL: https://github.com/rmarkello/pypmi/archive/0.3.tar.gz
Platform: UNKNOWN
Classifier: Development Status :: 3 - Alpha
Classifier: Intended Audience :: Science/Research
Classifier: License :: OSI Approved :: BSD License
Classifier: Programming Language :: Python :: 3.6
Classifier: Programming Language :: Python :: 3.7
Requires-Dist: numpy (>=0.15)
Requires-Dist: pandas (>=0.21)
Requires-Dist: requests
Requires-Dist: scipy
Requires-Dist: tqdm
Provides-Extra: all
Requires-Dist: docker ; extra == 'all'
Requires-Dist: sphinx (>=1.2) ; extra == 'all'
Requires-Dist: pytest (>=3.6) ; extra == 'all'
Requires-Dist: pytest-cov ; extra == 'all'
Requires-Dist: pydicom (>=1.3.0) ; extra == 'all'
Requires-Dist: nibabel ; extra == 'all'
Requires-Dist: sphinx-rtd-theme ; extra == 'all'
Requires-Dist: pybids (>=0.9.3) ; extra == 'all'
Provides-Extra: bids
Requires-Dist: docker ; extra == 'bids'
Requires-Dist: nibabel ; extra == 'bids'
Requires-Dist: pybids (>=0.9.3) ; extra == 'bids'
Requires-Dist: pydicom (>=1.3.0) ; extra == 'bids'
Provides-Extra: doc
Requires-Dist: sphinx (>=1.2) ; extra == 'doc'
Requires-Dist: sphinx-rtd-theme ; extra == 'doc'
Provides-Extra: tests
Requires-Dist: pytest (>=3.6) ; extra == 'tests'
Requires-Dist: pytest-cov ; extra == 'tests'
